LICENSE
README.md
setup.py
mcppy/__init__.py
mcppy/block.py
mcppy/connection.py
mcppy/entity.py
mcppy/event.py
mcppy/logger.py
mcppy/minecraft.py
mcppy/settings.py
mcppy/util.py
mcppy/vec3.py
mcppy.egg-info/PKG-INFO
mcppy.egg-info/SOURCES.txt
mcppy.egg-info/dependency_links.txt
mcppy.egg-info/requires.txt
mcppy.egg-info/top_level.txt